pythonpip/__init__.py
pythonpip/__main__.py
pythonpip/teste.py
testepip-1.0.9.dist-info/METADATA
testepip-1.0.9.dist-info/WHEEL
testepip-1.0.9.dist-info/top_level.txt
testepip-1.0.9.dist-info/RECORD
