Metadata-Version: 2.1
Name: testepip
Version: 1.0.9
Summary: Teste de criação do pacote PIP
Home-page: UNKNOWN
Author: Allyson Vilar
Author-email: allyson.santana@inmetrics.com.br
License: MIT
Keywords: exemplo tutorial desenvolvimento
Platform: UNKNOWN
Classifier: Development Status :: 4 - Beta
Classifier: Intended Audience :: Developers
Classifier: Topic :: Education :: Testing
Classifier: License :: OSI Approved :: MIT License
Classifier: Programming Language :: Python :: 3
Classifier: Programming Language :: Python :: 3.2
Classifier: Programming Language :: Python :: 3.3
Classifier: Programming Language :: Python :: 3.4
Requires-Dist: sh (>=1.11)
